examples/__init__.py
examples/address_example.py
examples/basic_usage.py
examples/check_menu_response.py
examples/check_token_response.py
examples/couriers_example.py
examples/customer_example.py
examples/delivery_example.py
examples/dictionaries_example.py
examples/error_handling_example.py
examples/marketing_sources_example.py
examples/menu_by_id_example.py
examples/menu_detailed_example.py
examples/menu_example.py
examples/organization_info.py
examples/quick_test.py
examples/terminal_groups_example.py
examples/test_client.py
examples/token_example.py
iiko_pkg/__init__.py
iiko_pkg/client.py
iiko_pkg/constants.py
iiko_pkg/exceptions.py
iiko_pkg/utils.py
iiko_pkg/models/__init__.py
iiko_pkg/models/auth.py
iiko_pkg/models/common.py
iiko_pkg/models/delivery.py
iiko_pkg/models/menu.py
iiko_pkg/models/orders.py
iiko_pkg/models/organizations.py
iiko_pkg-0.1.2.dist-info/licenses/LICENSE
tests/__init__.py
tests/test_client.py
tests/test_constants.py
tests/test_exceptions.py
tests/test_models.py
tests/test_utils.py
iiko_pkg-0.1.2.dist-info/METADATA
iiko_pkg-0.1.2.dist-info/WHEEL
iiko_pkg-0.1.2.dist-info/top_level.txt
iiko_pkg-0.1.2.dist-info/RECORD
