Metadata-Version: 2.4
Name: iiko-pkg
Version: 0.1.2
Summary: Python library for iiko.services API
Home-page: https://github.com/yourusername/iiko-pkg
Author: Muhammad Ali
Author-email: example@example.com
License: MIT
Keywords: iiko,iikobiz,iikocard,iikodelivery,iiko-api,iikocloudapi,iiko-integration,iiko-python,python-iiko,iiko-example,restaurant-management,pos-system,food-delivery,delivery-management,telegram-bot,python3,uzbekistan,tashkent,restaurant-pos,cafe-automation,restoran-avtomatizatsiya,dostavka
Classifier: Development Status :: 3 - Alpha
Classifier: Intended Audience :: Developers
Classifier: License :: OSI Approved :: MIT License
Classifier: Programming Language :: Python :: 3
Classifier: Programming Language :: Python :: 3.7
Classifier: Programming Language :: Python :: 3.8
Classifier: Programming Language :: Python :: 3.9
Classifier: Programming Language :: Python :: 3.10
Requires-Python: >=3.7
License-File: LICENSE
Requires-Dist: requests>=2.25.0
Requires-Dist: pydantic>=2.0.0
Provides-Extra: dev
Requires-Dist: pytest>=6.0.0; extra == "dev"
Requires-Dist: pytest-cov>=2.10.0; extra == "dev"
Requires-Dist: black>=20.8b1; extra == "dev"
Requires-Dist: isort>=5.0.0; extra == "dev"
Requires-Dist: flake8>=3.8.0; extra == "dev"
Requires-Dist: mypy>=0.800; extra == "dev"
Requires-Dist: tox>=3.20.0; extra == "dev"
Dynamic: author
Dynamic: author-email
Dynamic: classifier
Dynamic: description
Dynamic: description-content-type
Dynamic: home-page
Dynamic: keywords
Dynamic: license-file
Dynamic: provides-extra
Dynamic: requires-dist
Dynamic: requires-python
Dynamic: summary
